interpret/__init__.py
interpret/_version.py
interpret/develop.py
interpret/api/__init__.py
interpret/api/base.py
interpret/api/templates.py
interpret/blackbox/__init__.py
interpret/blackbox/_lime.py
interpret/blackbox/_partialdependence.py
interpret/blackbox/_permutationimportance.py
interpret/blackbox/_sensitivity.py
interpret/blackbox/_shap.py
interpret/data/__init__.py
interpret/data/_response.py
interpret/ext/__init__.py
interpret/ext/examples.py
interpret/ext/extension.py
interpret/ext/extension_utils.py
interpret/ext/blackbox/__init__.py
interpret/ext/data/__init__.py
interpret/ext/glassbox/__init__.py
interpret/ext/greybox/__init__.py
interpret/ext/perf/__init__.py
interpret/ext/provider/__init__.py
interpret/glassbox/__init__.py
interpret/glassbox/_aplr.py
interpret/glassbox/_decisiontree.py
interpret/glassbox/_linear.py
interpret/glassbox/_skoperules.py
interpret/glassbox/_ebm/__init__.py
interpret/glassbox/_ebm/_bin.py
interpret/glassbox/_ebm/_boost.py
interpret/glassbox/_ebm/_ebm.py
interpret/glassbox/_ebm/_excel.py
interpret/glassbox/_ebm/_json.py
interpret/glassbox/_ebm/_merge_ebms.py
interpret/glassbox/_ebm/_multiclass.py
interpret/glassbox/_ebm/_tensor.py
interpret/glassbox/_ebm/_utils.py
interpret/glassbox/_ebm/_research/__init__.py
interpret/glassbox/_ebm/_research/_group_importance.py
interpret/greybox/__init__.py
interpret/greybox/_shaptree.py
interpret/greybox/_treeinterpreter.py
interpret/perf/__init__.py
interpret/perf/_curve.py
interpret/perf/_regression.py
interpret/privacy/__init__.py
interpret/provider/__init__.py
interpret/provider/_compute.py
interpret/provider/_environment.py
interpret/provider/_visualize.py
interpret/root/bld/lib/interpret-inline.js
interpret/root/bld/lib/interpret-inline.js.LICENSE.txt
interpret/root/bld/lib/libebm_linux_arm.so
interpret/root/bld/lib/libebm_linux_arm_debug.so
interpret/root/bld/lib/libebm_linux_x64.so
interpret/root/bld/lib/libebm_linux_x64_debug.so
interpret/root/bld/lib/libebm_mac_arm.dylib
interpret_core-0.7.2.dist-info/METADATA
interpret_core-0.7.2.dist-info/WHEEL
interpret_core-0.7.2.dist-info/entry_points.txt
interpret_core-0.7.2.dist-info/top_level.txt
interpret_core-0.7.2.dist-info/RECORD
