Metadata-Version: 2.4
Name: interpret-core
Version: 0.7.2
Summary: Fit interpretable models. Explain blackbox machine learning.
Home-page: https://github.com/interpretml/interpret
Author: The InterpretML Contributors
Author-email: interpret@microsoft.com
Classifier: Programming Language :: Python
Classifier: Programming Language :: Python :: 3
Classifier: Programming Language :: Python :: 3.9
Classifier: Programming Language :: Python :: 3.10
Classifier: Programming Language :: Python :: 3.11
Classifier: Programming Language :: Python :: 3.12
Classifier: Topic :: Scientific/Engineering :: Artificial Intelligence
Classifier: Development Status :: 3 - Alpha
Classifier: License :: OSI Approved :: MIT License
Classifier: Operating System :: OS Independent
Requires-Dist: numpy>=1.25
Requires-Dist: pandas>=0.19.2
Requires-Dist: scikit-learn>=0.18.1
Requires-Dist: joblib>=0.11
Provides-Extra: debug
Requires-Dist: psutil>=5.6.2; extra == "debug"
Provides-Extra: notebook
Requires-Dist: ipykernel>=4.10.0; extra == "notebook"
Requires-Dist: ipython>=5.5.0; extra == "notebook"
Provides-Extra: plotly
Requires-Dist: plotly>=3.8.1; extra == "plotly"
Provides-Extra: excel
Requires-Dist: Xlsxwriter>=3.0.1; extra == "excel"
Requires-Dist: dotsi>=0.0.3; extra == "excel"
Requires-Dist: seaborn>=0.13.2; extra == "excel"
Requires-Dist: matplotlib>=3.9.1; extra == "excel"
Provides-Extra: lime
Requires-Dist: lime>=0.1.1.33; extra == "lime"
Provides-Extra: sensitivity
Requires-Dist: SALib>=1.3.3; extra == "sensitivity"
Provides-Extra: shap
Requires-Dist: shap>=0.28.5; extra == "shap"
Requires-Dist: dill>=0.2.5; extra == "shap"
Provides-Extra: linear
Provides-Extra: skoperules
Requires-Dist: skope-rules>=1.0.1; extra == "skoperules"
Provides-Extra: treeinterpreter
Requires-Dist: treeinterpreter>=0.2.2; extra == "treeinterpreter"
Provides-Extra: aplr
Requires-Dist: aplr>=10.6.1; extra == "aplr"
Provides-Extra: dash
Requires-Dist: dash<3.0.0,>=2.0.0; extra == "dash"
Requires-Dist: dash-cytoscape>=0.1.1; extra == "dash"
Requires-Dist: gevent>=1.3.6; extra == "dash"
Requires-Dist: requests>=2.19.0; extra == "dash"
Provides-Extra: testing
Requires-Dist: scipy>=0.18.1; extra == "testing"
Requires-Dist: scikit-learn>=1.0.0; extra == "testing"
Requires-Dist: pytest>=4.3.0; extra == "testing"
Requires-Dist: pytest-runner>=4.4; extra == "testing"
Requires-Dist: pytest-xdist>=1.29; extra == "testing"
Requires-Dist: nbconvert>=5.4.1; extra == "testing"
Requires-Dist: selenium>=3.141.0; extra == "testing"
Requires-Dist: pytest-cov>=2.6.1; extra == "testing"
Requires-Dist: ruff>=0.1.2; extra == "testing"
Requires-Dist: jupyter>=1.0.0; extra == "testing"
Requires-Dist: ipywidgets>=7.4.2; extra == "testing"
Dynamic: author
Dynamic: author-email
Dynamic: classifier
Dynamic: description
Dynamic: home-page
Dynamic: provides-extra
Dynamic: requires-dist
Dynamic: summary
